pishockpy/__init__.py
pishockpy-0.0.4.dist-info/LICENSE
pishockpy-0.0.4.dist-info/METADATA
pishockpy-0.0.4.dist-info/WHEEL
pishockpy-0.0.4.dist-info/top_level.txt
pishockpy-0.0.4.dist-info/RECORD
