Metadata-Version: 2.1
Name: pishockpy
Version: 0.0.4
Summary: Control a PiShock via the API.
Home-page: https://github.com/UWUplus/pishockpy
Author: Ralf Rademacher
Keywords: pishock
Classifier: Programming Language :: Python :: 3
Classifier: License :: OSI Approved :: GNU General Public License v3 (GPLv3)
Classifier: Operating System :: OS Independent
License-File: LICENSE
Requires-Dist: requests
